<?xml version="1.0" encoding="utf-8"?>
<Aircraft name="car-system" url="" theme="Default" size="6.303226,3.566435,9.75" boundsMin="-3.151611,1.029421,-4.875" xmlVersion="6" legacyJointIdentification="false">
  <Assembly>
    <Parts>
      <Part id="4" partType="Fuselage-Body-1" position="1.668929E-06,2.720858,3.625" rotation="0,0,0" drag="0.3293478,0.3293478,0.9704248,0.9704248,0.3445966,0.3445966" materials="0">
        <FuelTank.State fuel="175.78125" capacity="175.78125" />
        <Fuselage.State version="2" frontScale="1,1" rearScale="1,1" offset="0,0,5" deadWeight="0" buoyancy="0" fuelPercentage="1" autoSizeOnConnected="false" cornerTypes="1,1,1,1,1,1,1,1" />
      </Part>
      <Part id="5" partType="Fuselage-Body-1" position="1.668929E-06,2.220858,3.625" rotation="0,180,0" drag="0.2696,0.2696,0.3698832,0.3698832,0.01307167,0.01307167" materials="0">
        <FuelTank.State fuel="0" capacity="0" />
        <Fuselage.State version="2" frontScale="1,1" rearScale="1,1" offset="0,0,1" deadWeight="0" buoyancy="0" fuelPercentage="0" autoSizeOnConnected="false" cornerTypes="1,1,1,1,1,1,1,1" />
      </Part>
      <Part id="6" partType="Fuselage-Body-1" position="1.125005,3.283358,3.625" rotation="0,270,0" drag="0.3830164,0.3830164,0.2284716,0.2284716,0.08028314,0.1343127" materials="0">
        <FuelTank.State fuel="0" capacity="0" />
        <Fuselage.State version="2" frontScale="0.5,0.5" rearScale="0.5,0.5" offset="0,2.25,3.5" deadWeight="0" buoyancy="0" fuelPercentage="0" autoSizeOnConnected="false" cornerTypes="1,1,1,1,1,1,1,1" />
      </Part>
      <Part id="10" partType="Wheel-Resizable-1" position="2.35002,2.158358,3.625" rotation="0,180,0" drag="0.151,0.151,0.169,0.169,0.2057506,0.152" materials="6,4,4">
        <ResizableWheel.State turningAngle="15" engineId="75" direction="Normal" size="4.6" width="0.9" tire="Tractor" damper="1" spring="1" enableSuspension="false" enableAutoTraction="false" turningRate="150" maxAngularVelocity="300" brakeTorque="50" slipForwardExtremum="8" slipForwardAsymptote="10" slipSidewaysExtremum="15" slipSidewaysAsymptote="20" tractionForward="1.5" tractionSideways="1.5" />
        <InputController.State activationGroup="0" invert="false" min="-1" max="1" input="Yaw" zeroOnDeactivate="false" />
      </Part>
      <Part id="11" partType="Fuselage-Body-1" position="2.125017,2.220858,3.625" rotation="0,270,0" drag="0.0635,0.0635,0.0645,0.0645,0.0004292198,0" materials="0">
        <FuelTank.State fuel="0" capacity="0" />
        <Fuselage.State version="2" frontScale="0.5,0.5" rearScale="0.5,0.5" offset="0,0,0.5" deadWeight="0" buoyancy="0" fuelPercentage="0" autoSizeOnConnected="false" cornerTypes="1,1,1,1,1,1,1,1" />
      </Part>
      <Part id="12" partType="Fuselage-Body-1" position="2.125005,3.845856,3.625" rotation="0,270,0" drag="0,0,0,0,0,0" materials="0">
        <FuelTank.State fuel="0" capacity="0" />
        <Fuselage.State version="2" frontScale="0.5,0.5" rearScale="0.5,0.5" offset="0,0,0.5" deadWeight="0" buoyancy="0" fuelPercentage="0" autoSizeOnConnected="false" cornerTypes="1,1,1,1,1,1,1,1" />
      </Part>
      <Part id="13" partType="HingeRotator-1" position="2.125005,3.720857,3.625" rotation="90,0,0" drag="0.0635,0.0635,0.0015168,0.0015168,0.0008392916,0.0641" materials="0,3,10">
        <InputController.State activationGroup="0" invert="false" min="-1" max="1" input="Disabled" />
        <JointRotator.State range="90" speed="0" />
      </Part>
      <Part id="14" partType="Shock" position="2.125017,2.908358,3.625" rotation="0,0,180" drag="0.251,0.251,0.0081216,0.0081216,0.005291289,0.0004" materials="0,1,3" scale="2.000013,2.25,2.000007">
        <Suspension.State damper="2.5" spring="1" />
      </Part>
      <Part id="15" partType="Fuselage-Body-1" position="-1.124997,3.283358,3.625" rotation="0,90,0" drag="0.3830164,0.3830164,0.2284717,0.2284717,0.16811,0.08028073" materials="0">
        <FuelTank.State fuel="0" capacity="0" />
        <Fuselage.State version="2" frontScale="0.5,0.5" rearScale="0.5,0.5" offset="0,2.25,3.5" deadWeight="0" buoyancy="0" fuelPercentage="0" autoSizeOnConnected="false" cornerTypes="1,1,1,1,1,1,1,1" />
      </Part>
      <Part id="16" partType="Fuselage-Body-1" position="-2.125,3.845856,3.625" rotation="0,90,0" drag="0,0,0,0,0,0" materials="0">
        <FuelTank.State fuel="0" capacity="0" />
        <Fuselage.State version="2" frontScale="0.5,0.5" rearScale="0.5,0.5" offset="0,0,0.5" deadWeight="0" buoyancy="0" fuelPercentage="0" autoSizeOnConnected="false" cornerTypes="1,1,1,1,1,1,1,1" />
      </Part>
      <Part id="17" partType="HingeRotator-1" position="-2.125,3.720857,3.625" rotation="90,0,0" drag="0.0635,0.0635,0.0015168,0.0015168,0.0016,0.0008392264" materials="0,3,10">
        <InputController.State activationGroup="0" invert="true" min="-1" max="1" input="Disabled" />
        <JointRotator.State range="90" speed="0" />
      </Part>
      <Part id="18" partType="Shock" position="-2.125009,2.908358,3.625" rotation="0,0,180" drag="0.251,0.251,0.0081216,0.0081216,0.0004,0.005284264" materials="0,1,3" scale="2.000013,2.25,2.000007">
        <Suspension.State damper="2.5" spring="1" />
      </Part>
      <Part id="19" partType="HingeRotator-1" position="-0.2499988,2.220858,3.625" rotation="0,270,270" drag="0.0645,0.0645,0.0645,0.0645,0.0001010688,0.0001010615" materials="0,3,10">
        <InputController.State activationGroup="0" invert="true" min="-1" max="1" input="Disabled" />
        <JointRotator.State range="90" speed="0" />
      </Part>
      <Part id="35" partType="Fuselage-Body-1" position="1.668927E-06,2.720858,-5.684342E-14" rotation="0,0,0" drag="0.02962472,0.02962472,1.216021,1.216021,1.190951,1.190951" materials="0">
        <FuelTank.State fuel="298.828125" capacity="298.828125" />
        <Fuselage.State version="2" frontScale="1,1" rearScale="1,1" offset="0,0,8.5" deadWeight="453.5929" buoyancy="0" fuelPercentage="1" autoSizeOnConnected="false" cornerTypes="1,1,1,1,1,1,1,1" />
      </Part>
      <Part id="37" partType="Cockpit-4" position="7.450578E-07,4.345856,0" rotation="0,0,0" drag="0.1846247,0.1846247,0,0,0.1874678,0.1874678" materials="7,0,1">
        <Cockpit.State primaryCockpit="True" lookBackTranslation="0,0" />
      </Part>
      <Part id="39" partType="Fuselage-Body-1" position="-2.125009,2.220858,3.625" rotation="0,90,0" drag="0.0635,0.0635,0.0645,0.0645,0,0.000428776" materials="0">
        <FuelTank.State fuel="0" capacity="0" />
        <Fuselage.State version="2" frontScale="0.5,0.5" rearScale="0.5,0.5" offset="0,0,0.5" deadWeight="0" buoyancy="0" fuelPercentage="0" autoSizeOnConnected="false" cornerTypes="1,1,1,1,1,1,1,1" />
      </Part>
      <Part id="40" partType="Wheel-Resizable-1" position="-2.350012,2.158358,3.625" rotation="0,-1.001791E-05,0" drag="0.152,0.152,0.2456322,0.2456322,0.2390002,0.1515922" materials="6,4,4">
        <ResizableWheel.State turningAngle="15" engineId="75" direction="Reversed" size="4.6" width="0.9" tire="Tractor" damper="1" spring="1" enableSuspension="false" enableAutoTraction="false" turningRate="150" maxAngularVelocity="300" brakeTorque="50" slipForwardExtremum="8" slipForwardAsymptote="10" slipSidewaysExtremum="15" slipSidewaysAsymptote="20" tractionForward="1.5" tractionSideways="1.5" />
        <InputController.State activationGroup="0" invert="false" min="-1" max="1" input="Yaw" zeroOnDeactivate="false" />
      </Part>
      <Part id="41" partType="Fuselage-Body-1" position="1.668929E-06,2.720858,-3.625" rotation="0,0,0" drag="0.0188663,0.0188663,0.9704248,0.9704248,0.3445966,0.3445966" materials="0">
        <FuelTank.State fuel="175.78125" capacity="175.78125" />
        <Fuselage.State version="2" frontScale="1,1" rearScale="1,1" offset="0,0,5" deadWeight="0" buoyancy="0" fuelPercentage="1" autoSizeOnConnected="false" cornerTypes="1,1,1,1,1,1,1,1" />
      </Part>
      <Part id="42" partType="Fuselage-Body-1" position="1.668929E-06,2.220858,-3.625" rotation="0,180,0" drag="0.1007934,0.1007934,0.3698832,0.3698832,0.01307167,0.01307167" materials="0">
        <FuelTank.State fuel="0" capacity="0" />
        <Fuselage.State version="2" frontScale="1,1" rearScale="1,1" offset="0,0,1" deadWeight="0" buoyancy="0" fuelPercentage="0" autoSizeOnConnected="false" cornerTypes="1,1,1,1,1,1,1,1" />
      </Part>
      <Part id="45" partType="Fuselage-Body-1" position="-2.125016,2.220858,-3.625" rotation="0,90,0" drag="0.02883682,0.02883682,0.0645,0.0645,0,0.000428776" materials="0">
        <FuelTank.State fuel="0" capacity="0" />
        <Fuselage.State version="2" frontScale="0.5,0.5" rearScale="0.5,0.5" offset="0,0,0.5" deadWeight="0" buoyancy="0" fuelPercentage="0" autoSizeOnConnected="false" cornerTypes="1,1,1,1,1,1,1,1" />
      </Part>
      <Part id="46" partType="Wheel-Resizable-1" position="-2.350016,2.158358,-3.625" rotation="0,-1.001791E-05,0" drag="0.1508861,0.1508861,0.2456322,0.2456322,0.2390002,0.1504511" materials="6,4,4">
        <ResizableWheel.State turningAngle="0" engineId="75" direction="Reversed" size="4.6" width="0.9" tire="Tractor" damper="1" spring="1" enableSuspension="false" enableAutoTraction="false" turningRate="150" maxAngularVelocity="300" brakeTorque="50" slipForwardExtremum="8" slipForwardAsymptote="10" slipSidewaysExtremum="15" slipSidewaysAsymptote="20" tractionForward="1.5" tractionSideways="1.5" />
        <InputController.State activationGroup="0" invert="false" min="-1" max="1" input="Yaw" zeroOnDeactivate="false" />
      </Part>
      <Part id="47" partType="Shock" position="-2.125016,2.908358,-3.625" rotation="0,0,180" drag="0.07628937,0.07628937,0.0081216,0.0081216,0.0004,0.005284264" materials="0,1,3" scale="2.000013,2.25,2.000007">
        <Suspension.State damper="2.5" spring="1" />
      </Part>
      <Part id="48" partType="HingeRotator-1" position="-2.125005,3.720857,-3.625" rotation="90,0,0" drag="0.02707056,0.02707056,0.0015168,0.0015168,0.0016,0.0008392263" materials="0,3,10">
        <InputController.State activationGroup="0" invert="true" min="-1" max="1" input="Disabled" />
        <JointRotator.State range="90" speed="0" />
      </Part>
      <Part id="49" partType="Fuselage-Body-1" position="-2.125005,3.845856,-3.625" rotation="0,90,0" drag="0,0,0,0,0,0" materials="0">
        <FuelTank.State fuel="0" capacity="0" />
        <Fuselage.State version="2" frontScale="0.5,0.5" rearScale="0.5,0.5" offset="0,0,0.5" deadWeight="0" buoyancy="0" fuelPercentage="0" autoSizeOnConnected="false" cornerTypes="1,1,1,1,1,1,1,1" />
      </Part>
      <Part id="50" partType="Fuselage-Body-1" position="-1.125006,3.283358,-3.625" rotation="0,90,0" drag="0.09163851,0.09163851,0.2284717,0.2284717,0.16811,0.08028073" materials="0">
        <FuelTank.State fuel="0" capacity="0" />
        <Fuselage.State version="2" frontScale="0.5,0.5" rearScale="0.5,0.5" offset="0,2.25,3.5" deadWeight="0" buoyancy="0" fuelPercentage="0" autoSizeOnConnected="false" cornerTypes="1,1,1,1,1,1,1,1" />
      </Part>
      <Part id="51" partType="HingeRotator-1" position="0.250002,2.220858,-3.625" rotation="0,90,90" drag="0.03829084,0.03829084,0.0645,0.0645,0.0001010615,0.0001010688" materials="0,3,10">
        <InputController.State activationGroup="0" invert="false" min="-1" max="1" input="Disabled" />
        <JointRotator.State range="90" speed="0" />
      </Part>
      <Part id="53" partType="Fuselage-Body-1" position="2.125013,2.220858,-3.625" rotation="0,270,0" drag="0.03007736,0.03007736,0.0645,0.0645,0.000428776,0" materials="0">
        <FuelTank.State fuel="0" capacity="0" />
        <Fuselage.State version="2" frontScale="0.5,0.5" rearScale="0.5,0.5" offset="0,0,0.5" deadWeight="0" buoyancy="0" fuelPercentage="0" autoSizeOnConnected="false" cornerTypes="1,1,1,1,1,1,1,1" />
      </Part>
      <Part id="54" partType="Wheel-Resizable-1" position="2.350018,2.158359,-3.625" rotation="0,180,0" drag="0.1508723,0.1508723,0.169,0.169,0.2039905,0.152" materials="6,4,4">
        <ResizableWheel.State turningAngle="0" engineId="75" direction="Normal" size="4.6" width="0.9" tire="Tractor" damper="1" spring="1" enableSuspension="false" enableAutoTraction="false" turningRate="150" maxAngularVelocity="300" brakeTorque="50" slipForwardExtremum="8" slipForwardAsymptote="10" slipSidewaysExtremum="15" slipSidewaysAsymptote="20" tractionForward="1.5" tractionSideways="1.5" />
        <InputController.State activationGroup="0" invert="false" min="-1" max="1" input="Yaw" zeroOnDeactivate="false" />
      </Part>
      <Part id="55" partType="Shock" position="2.125013,2.908358,-3.625" rotation="0,0,180" drag="0.08800774,0.08800774,0.0081216,0.0081216,0.005284264,0.0004" materials="0,1,3" scale="2.000013,2.25,2.000007">
        <Suspension.State damper="2.5" spring="1" />
      </Part>
      <Part id="56" partType="HingeRotator-1" position="2.125003,3.720857,-3.625" rotation="90,0,0" drag="0.02833366,0.02833366,0.0015168,0.0015168,0.0008392263,0.0641" materials="0,3,10">
        <InputController.State activationGroup="0" invert="false" min="-1" max="1" input="Disabled" />
        <JointRotator.State range="90" speed="0" />
      </Part>
      <Part id="57" partType="Fuselage-Body-1" position="2.125003,3.845856,-3.625" rotation="0,270,0" drag="0,0,0,0,0,0" materials="0">
        <FuelTank.State fuel="0" capacity="0" />
        <Fuselage.State version="2" frontScale="0.5,0.5" rearScale="0.5,0.5" offset="0,0,0.5" deadWeight="0" buoyancy="0" fuelPercentage="0" autoSizeOnConnected="false" cornerTypes="1,1,1,1,1,1,1,1" />
      </Part>
      <Part id="58" partType="Fuselage-Body-1" position="1.125002,3.283358,-3.625" rotation="0,270,0" drag="0.09056473,0.09056473,0.2284716,0.2284716,0.08028074,0.1343127" materials="0">
        <FuelTank.State fuel="0" capacity="0" />
        <Fuselage.State version="2" frontScale="0.5,0.5" rearScale="0.5,0.5" offset="0,2.25,3.5" deadWeight="0" buoyancy="0" fuelPercentage="0" autoSizeOnConnected="false" cornerTypes="1,1,1,1,1,1,1,1" />
      </Part>
      <Part id="59" partType="Fuselage-Body-1" position="7.450549E-07,3.470857,-5.684342E-14" rotation="0,0,0" drag="2.544134,2.544134,7.212952,7.212952,2.883529,2.882212" materials="0">
        <FuelTank.State fuel="0" capacity="0" />
        <Fuselage.State version="2" frontScale="5,2" rearScale="5,2" offset="0,0,8.5" deadWeight="0" buoyancy="0" fuelPercentage="0" autoSizeOnConnected="false" cornerTypes="1,1,1,1,1,1,1,1" />
      </Part>
      <Part id="60" partType="Fuselage-Body-1" position="-2.354387E-06,2.720858,-1.75" rotation="0,90,0" drag="0.5520094,0.5520094,2.099786,2.099786,0.3438953,0.3438953" materials="0">
        <FuelTank.State fuel="298.828125" capacity="298.828125" />
        <Fuselage.State version="2" frontScale="1,1" rearScale="1,1" offset="0,0,8.5" deadWeight="0" buoyancy="0" fuelPercentage="1" autoSizeOnConnected="false" cornerTypes="1,1,1,1,1,1,1,1" />
      </Part>
      <Part id="66" partType="Fuselage-Body-1" position="1.668927E-06,2.720858,1.75" rotation="0,270,0" drag="1.299294,1.299294,2.214289,2.214289,0.3466646,0.3438953" materials="0">
        <FuelTank.State fuel="298.828125" capacity="298.828125" />
        <Fuselage.State version="2" frontScale="1,1" rearScale="1,1" offset="0,0,8.5" deadWeight="0" buoyancy="0" fuelPercentage="1" autoSizeOnConnected="false" cornerTypes="1,1,1,1,1,1,1,1" />
      </Part>
      <Part id="75" partType="Car-Engine-1" position="-3.337863E-06,2.720858,-5.684342E-14" rotation="0,0,0" drag="0.01260665,0.01260665,0.5159999,0.5159999,0.758,0.7580001" materials="1,3,10">
        <CarEngine.State power="600" />
        <InputController.State activationGroup="0" invert="false" min="-1" max="1" input="Trim" zeroOnDeactivate="false" />
      </Part>
      <Part id="78" partType="HingeRotator-1" position="-2.125,3.845856,3.625" rotation="0,180,270" drag="0.003,0.003,0.001493171,0.001493171,0.003,0.002288739" materials="0,3,10">
        <InputController.State activationGroup="0" invert="true" min="-1" max="1" input="Disabled" />
        <JointRotator.State range="90" speed="0" />
      </Part>
      <Part id="79" partType="HingeRotator-1" position="-2.125005,3.845856,-3.625" rotation="0,0,270" drag="0.002275165,0.002275165,0.001493171,0.001493171,0.003,0.002288738" materials="0,3,10">
        <InputController.State activationGroup="0" invert="true" min="-1" max="1" input="Disabled" />
        <JointRotator.State range="90" speed="0" />
      </Part>
      <Part id="83" partType="HingeRotator-1" position="2.125005,3.845856,3.625" rotation="0,180,270" drag="0.003,0.003,0.001493171,0.001493171,0.002288739,0.003" materials="0,3,10">
        <InputController.State activationGroup="0" invert="true" min="-1" max="1" input="Disabled" />
        <JointRotator.State range="90" speed="0" />
      </Part>
      <Part id="84" partType="HingeRotator-1" position="2.125003,3.845856,-3.625" rotation="0,0,270" drag="0.002277808,0.002277808,0.001493171,0.001493171,0.002288738,0.003" materials="0,3,10">
        <InputController.State activationGroup="0" invert="true" min="-1" max="1" input="Disabled" />
        <JointRotator.State range="90" speed="0" />
      </Part>
      <Part id="85" partType="Fuselage-Body-1" position="7.450549E-07,3.845856,-5.684342E-14" rotation="0,90,0" drag="0.7792692,0.7792692,1.211273,1.211273,0.2920865,0.2920867" materials="0">
        <FuelTank.State fuel="0" capacity="0" />
        <Fuselage.State version="2" frontScale="1,1" rearScale="1,1" offset="0,0,10" deadWeight="0" buoyancy="0" fuelPercentage="0" autoSizeOnConnected="false" cornerTypes="1,1,1,1,1,1,1,1" />
      </Part>
      <Part id="88" partType="Shock" position="-2.125,3.845856,1.937501" rotation="0,90,90" drag="0.183153,0.183153,0.6413221,0.6413221,1.5232,0.4925245" materials="0,1,3" scale="2.000008,5.75,2.000001">
        <Suspension.State damper="2.5" spring="1" />
      </Part>
      <Part id="89" partType="HingeRotator-1" position="-0.2499974,2.220858,-3.625" rotation="0,270,270" drag="0.03829084,0.03829084,0.0645,0.0645,0.0001010688,0.0001010615" materials="0,3,10">
        <InputController.State activationGroup="0" invert="true" min="-1" max="1" input="Disabled" />
        <JointRotator.State range="90" speed="0" />
      </Part>
      <Part id="90" partType="Shock" position="1.250005,2.220858,-3.625" rotation="0,0,90.00001" drag="0.2054141,0.2054141,0.387,0.387,0.001838469,0.0001135104" materials="0,1,3" scale="2.000016,3,2.000007">
        <Suspension.State damper="2.5" spring="1.6" />
      </Part>
      <Part id="91" partType="Shock" position="1.250006,2.220858,3.625" rotation="0,0,90.00001" drag="0.387,0.387,0.387,0.387,0.001838721,0.0001135104" materials="0,1,3" scale="2.000016,3,2.000007">
        <Suspension.State damper="2.5" spring="1.6" />
      </Part>
      <Part id="92" partType="Shock" position="-1.249995,2.220858,3.625" rotation="0,0,270" drag="0.3870001,0.3870001,0.387,0.387,0.0001135104,0.001838469" materials="0,1,3" scale="2.000016,3,2.000007">
        <Suspension.State damper="2.5" spring="1.6" />
      </Part>
      <Part id="93" partType="Shock" position="-1.249993,2.220858,-3.625" rotation="0,0,270" drag="0.2039318,0.2039318,0.387,0.387,0.0001135104,0.001838469" materials="0,1,3" scale="2.000016,3,2.000007">
        <Suspension.State damper="2.5" spring="1.6" />
      </Part>
      <Part id="94" partType="HingeRotator-1" position="0.2500028,2.220858,3.625" rotation="0,90,90" drag="0.0645,0.0645,0.0645,0.0645,0.0001010615,0.0001010688" materials="0,3,10">
        <InputController.State activationGroup="0" invert="false" min="-1" max="1" input="Disabled" />
        <JointRotator.State range="90" speed="0" />
      </Part>
      <Part id="95" partType="HingeRotator-1" position="1.668929E-06,2.720858,2.125" rotation="0,0,270" drag="0.00133056,0.00133056,0.002,0.002,0,0.0455256" materials="0,3,10">
        <InputController.State activationGroup="0" invert="false" min="-1" max="1" input="Disabled" />
        <JointRotator.State range="90" speed="0" />
      </Part>
      <Part id="96" partType="HingeRotator-1" position="-2.125,3.845856,0.2500005" rotation="0,0,270" drag="0.004734697,0.004734697,0.06649999,0.06649999,0.002,0.0006668637" materials="0,3,10">
        <InputController.State activationGroup="0" invert="true" min="-1" max="1" input="Disabled" />
        <JointRotator.State range="90" speed="0" />
      </Part>
      <Part id="97" partType="HingeRotator-1" position="2.125006,3.845856,0.2500005" rotation="0,0,90" drag="0.004734697,0.004734697,0.06649999,0.06649999,0.0006668637,0.002" materials="0,3,10">
        <InputController.State activationGroup="0" invert="false" min="-1" max="1" input="Disabled" />
        <JointRotator.State range="90" speed="0" />
      </Part>
      <Part id="98" partType="Shock" position="2.125005,3.845856,1.9375" rotation="0,90,90" drag="0.183153,0.183153,0.6413221,0.6413221,0.4926578,1.5232" materials="0,1,3" scale="2.000008,5.75,2.000001">
        <Suspension.State damper="2.5" spring="1" />
      </Part>
      <Part id="99" partType="HingeRotator-1" position="1.668929E-06,2.720858,-2.125" rotation="0,180,270" drag="0.0002175724,0.0002175724,0.002,0.002,0.0455256,0.0455256" materials="0,3,10">
        <InputController.State activationGroup="0" invert="false" min="-1" max="1" input="Disabled" />
        <JointRotator.State range="90" speed="0" />
      </Part>
      <Part id="100" partType="HingeRotator-1" position="2.125003,3.845856,-0.2500003" rotation="0,180,270" drag="0.002409225,0.002409225,0.06649999,0.06649999,0.0006565065,0.002" materials="0,3,10">
        <InputController.State activationGroup="0" invert="true" min="-1" max="1" input="Disabled" />
        <JointRotator.State range="90" speed="0" />
      </Part>
      <Part id="101" partType="HingeRotator-1" position="-2.124998,3.845856,-0.2500003" rotation="0,180,90" drag="0.002409225,0.002409225,0.06649999,0.06649999,0.002,0.0006565065" materials="0,3,10">
        <InputController.State activationGroup="0" invert="false" min="-1" max="1" input="Disabled" />
        <JointRotator.State range="90" speed="0" />
      </Part>
      <Part id="102" partType="Shock" position="-2.124998,3.845856,-1.9375" rotation="0,90,90" drag="0.04049656,0.04049656,0.641322,0.641322,1.5232,0.4916814" materials="0,1,3" scale="2.000008,5.75,2.000001">
        <Suspension.State damper="2.5" spring="1" />
      </Part>
      <Part id="103" partType="Shock" position="2.125003,3.845856,-1.937502" rotation="0,90,90" drag="0.04060004,0.04060004,0.6978197,0.6978197,0.4916814,1.5232" materials="0,1,3" scale="2.000008,5.75,2.000001">
        <Suspension.State damper="2.5" spring="1" />
      </Part>
    </Parts>
    <Connections>
      <Connection partA="5" partB="4" attachPointsA="3" attachPointsB="4" />
      <Connection partA="6" partB="4" attachPointsA="0" attachPointsB="5" />
      <Connection partA="15" partB="4" attachPointsA="0" attachPointsB="6" />
      <Connection partA="4" partB="95" attachPointsA="1" attachPointsB="0" />
      <Connection partA="19" partB="5" attachPointsA="1" attachPointsB="5" />
      <Connection partA="94" partB="5" attachPointsA="1" attachPointsB="6" />
      <Connection partA="12" partB="6" attachPointsA="0" attachPointsB="1" />
      <Connection partA="10" partB="11" attachPointsA="0" attachPointsB="1" />
      <Connection partA="14" partB="11" attachPointsA="0" attachPointsB="3" />
      <Connection partA="91" partB="11" attachPointsA="1" attachPointsB="0" />
      <Connection partA="13" partB="12" attachPointsA="1" attachPointsB="4" />
      <Connection partA="83" partB="12" attachPointsA="1" attachPointsB="2" />
      <Connection partA="14" partB="13" attachPointsA="1" attachPointsB="0" />
      <Connection partA="16" partB="15" attachPointsA="0" attachPointsB="1" />
      <Connection partA="17" partB="16" attachPointsA="1" attachPointsB="4" />
      <Connection partA="78" partB="16" attachPointsA="1" attachPointsB="2" />
      <Connection partA="18" partB="17" attachPointsA="1" attachPointsB="0" />
      <Connection partA="18" partB="39" attachPointsA="0" attachPointsB="3" />
      <Connection partA="92" partB="19" attachPointsA="0" attachPointsB="0" />
      <Connection partA="59" partB="35" attachPointsA="4" attachPointsB="3" />
      <Connection partA="60" partB="35" attachPointsA="1" attachPointsB="2" />
      <Connection partA="66" partB="35" attachPointsA="3" attachPointsB="2" />
      <Connection partA="75" partB="35" attachPointsA="4,5" attachPointsB="4,2" />
      <Connection partA="95" partB="35" attachPointsA="1" attachPointsB="0" />
      <Connection partA="99" partB="35" attachPointsA="1" attachPointsB="1" />
      <Connection partA="37" partB="85" attachPointsA="1" attachPointsB="3" />
      <Connection partA="40" partB="39" attachPointsA="0" attachPointsB="1" />
      <Connection partA="92" partB="39" attachPointsA="1" attachPointsB="0" />
      <Connection partA="42" partB="41" attachPointsA="3" attachPointsB="4" />
      <Connection partA="50" partB="41" attachPointsA="0" attachPointsB="6" />
      <Connection partA="58" partB="41" attachPointsA="0" attachPointsB="5" />
      <Connection partA="41" partB="99" attachPointsA="0" attachPointsB="0" />
      <Connection partA="51" partB="42" attachPointsA="1" attachPointsB="6" />
      <Connection partA="89" partB="42" attachPointsA="1" attachPointsB="5" />
      <Connection partA="46" partB="45" attachPointsA="0" attachPointsB="1" />
      <Connection partA="47" partB="45" attachPointsA="0" attachPointsB="3" />
      <Connection partA="93" partB="45" attachPointsA="1" attachPointsB="0" />
      <Connection partA="47" partB="48" attachPointsA="1" attachPointsB="0" />
      <Connection partA="48" partB="49" attachPointsA="1" attachPointsB="4" />
      <Connection partA="49" partB="50" attachPointsA="0" attachPointsB="1" />
      <Connection partA="79" partB="49" attachPointsA="1" attachPointsB="2" />
      <Connection partA="90" partB="51" attachPointsA="0" attachPointsB="0" />
      <Connection partA="54" partB="53" attachPointsA="0" attachPointsB="1" />
      <Connection partA="55" partB="53" attachPointsA="0" attachPointsB="3" />
      <Connection partA="90" partB="53" attachPointsA="1" attachPointsB="0" />
      <Connection partA="55" partB="56" attachPointsA="1" attachPointsB="0" />
      <Connection partA="56" partB="57" attachPointsA="1" attachPointsB="4" />
      <Connection partA="57" partB="58" attachPointsA="0" attachPointsB="1" />
      <Connection partA="84" partB="57" attachPointsA="1" attachPointsB="2" />
      <Connection partA="85" partB="59" attachPointsA="0" attachPointsB="2" />
      <Connection partA="88" partB="78" attachPointsA="0" attachPointsB="0" />
      <Connection partA="102" partB="79" attachPointsA="1" attachPointsB="0" />
      <Connection partA="98" partB="83" attachPointsA="0" attachPointsB="0" />
      <Connection partA="103" partB="84" attachPointsA="1" attachPointsB="0" />
      <Connection partA="96" partB="85" attachPointsA="1" attachPointsB="2" />
      <Connection partA="97" partB="85" attachPointsA="1" attachPointsB="2" />
      <Connection partA="100" partB="85" attachPointsA="1" attachPointsB="2" />
      <Connection partA="101" partB="85" attachPointsA="1" attachPointsB="2" />
      <Connection partA="88" partB="96" attachPointsA="1" attachPointsB="0" />
      <Connection partA="93" partB="89" attachPointsA="0" attachPointsB="0" />
      <Connection partA="91" partB="94" attachPointsA="0" attachPointsB="0" />
      <Connection partA="98" partB="97" attachPointsA="1" attachPointsB="0" />
      <Connection partA="103" partB="100" attachPointsA="0" attachPointsB="0" />
      <Connection partA="102" partB="101" attachPointsA="0" attachPointsB="0" />
    </Connections>
    <Bodies>
      <Body partIds="4,5,19,94,6,12,13,83,15,16,17,78" position="0,0,0" rotation="0,0,0" velocity="0,0,0" angularVelocity="0,0,0" />
      <Body partIds="10" position="0,0,0" rotation="0,0,0" velocity="0,0,0" angularVelocity="0,0,0" />
      <Body partIds="11" position="0,0,0" rotation="0,0,0" velocity="0,0,0" angularVelocity="0,0,0" />
      <Body partIds="14" position="0,0,0" rotation="0,0,0" velocity="0,0,0" angularVelocity="0,0,0" />
      <Body partIds="18" position="0,0,0" rotation="0,0,0" velocity="0,0,0" angularVelocity="0,0,0" />
      <Body partIds="35,59,85,37,96,97,100,101,60,66,75,95,99" position="0,0,0" rotation="0,0,0" velocity="0,0,0" angularVelocity="0,0,0" />
      <Body partIds="39" position="0,0,0" rotation="0,0,0" velocity="0,0,0" angularVelocity="0,0,0" />
      <Body partIds="40" position="0,0,0" rotation="0,0,0" velocity="0,0,0" angularVelocity="0,0,0" />
      <Body partIds="41,42,51,89,50,49,48,79,58,57,56,84" position="0,0,0" rotation="0,0,0" velocity="0,0,0" angularVelocity="0,0,0" />
      <Body partIds="45" position="0,0,0" rotation="0,0,0" velocity="0,0,0" angularVelocity="0,0,0" />
      <Body partIds="46" position="0,0,0" rotation="0,0,0" velocity="0,0,0" angularVelocity="0,0,0" />
      <Body partIds="47" position="0,0,0" rotation="0,0,0" velocity="0,0,0" angularVelocity="0,0,0" />
      <Body partIds="53" position="0,0,0" rotation="0,0,0" velocity="0,0,0" angularVelocity="0,0,0" />
      <Body partIds="54" position="0,0,0" rotation="0,0,0" velocity="0,0,0" angularVelocity="0,0,0" />
      <Body partIds="55" position="0,0,0" rotation="0,0,0" velocity="0,0,0" angularVelocity="0,0,0" />
      <Body partIds="88" position="0,0,0" rotation="0,0,0" velocity="0,0,0" angularVelocity="0,0,0" />
      <Body partIds="90" position="0,0,0" rotation="0,0,0" velocity="0,0,0" angularVelocity="0,0,0" />
      <Body partIds="91" position="0,0,0" rotation="0,0,0" velocity="0,0,0" angularVelocity="0,0,0" />
      <Body partIds="92" position="0,0,0" rotation="0,0,0" velocity="0,0,0" angularVelocity="0,0,0" />
      <Body partIds="93" position="0,0,0" rotation="0,0,0" velocity="0,0,0" angularVelocity="0,0,0" />
      <Body partIds="98" position="0,0,0" rotation="0,0,0" velocity="0,0,0" angularVelocity="0,0,0" />
      <Body partIds="102" position="0,0,0" rotation="0,0,0" velocity="0,0,0" angularVelocity="0,0,0" />
      <Body partIds="103" position="0,0,0" rotation="0,0,0" velocity="0,0,0" angularVelocity="0,0,0" />
    </Bodies>
  </Assembly>
  <Theme name="Custom">
    <Material color="E9E9E9" r="0.15" m="0.5" s="0.7" />
    <Material color="000000" r="0.3" m="0.5" s="0.83" />
    <Material color="001F7F" r="0.3" m="0.5" s="0.83" />
    <Material color="AA2A00" r="0.15" m="0.5" s="0.7" />
    <Material color="3F3F3F" r="0" m="0.65" s="0.08" />
    <Material color="5C0000" r="0" m="0.65" s="0.08" />
    <Material color="FFFFFF" r="0" m="0.65" s="0.08" />
    <Material color="FFF0F0" r="0" m="0.65" s="0.08" />
    <Material color="FF0F0F" r="0" m="0.65" s="0.08" />
    <Material color="AAAAAA" r="0" m="0.65" s="0.08" />
    <Material color="3F3F3F" r="0.15" m="0.5" s="0.7" />
    <Material color="ABABAB" r="0" m="0.65" s="0.08" />
    <Material color="446677" r="0" m="0.65" s="0.08" />
    <Material color="FF1143" r="0" m="0.65" s="0.08" />
    <Material color="FF6A12" r="0" m="0.65" s="0.08" />
    <Material color="000000" r="0" m="0.65" s="0.08" />
    <Material color="FFFFFF" r="0" m="0.65" s="0.08" />
    <Material color="1E1E1E" r="0" m="0.65" s="0.08" />
    <Material color="D0D0D0" r="0" m="0.65" s="0.08" />
  </Theme>
</Aircraft>